pip_split_requirements/__init__.py
pip_split_requirements/__main__.py
pip_split_requirements/_compat.py
pip_split_requirements/_split_requirements.py
pip_split_requirements-0.7.0.dist-info/METADATA
pip_split_requirements-0.7.0.dist-info/WHEEL
pip_split_requirements-0.7.0.dist-info/entry_points.txt
pip_split_requirements-0.7.0.dist-info/licenses/LICENSE.txt
pip_split_requirements-0.7.0.dist-info/RECORD
