Metadata-Version: 2.1
Name: pip-split-requirements
Version: 0.7.0
Project-URL: Documentation, https://github.com/sbidoul/pip-split-requirements#readme
Project-URL: Issues, https://github.com/sbidoul/pip-split-requirements/issues
Project-URL: Source, https://github.com/sbidoul/pip-split-requirements
Project-URL: Changelog, https://github.com/sbidoul/pip-split-requirements/releases
Author-email: Stéphane Bidoul <stephane.bidoul@acsone.eu>
License-Expression: MIT
License-File: LICENSE.txt
Classifier: Development Status :: 3 - Alpha
Classifier: Programming Language :: Python
Classifier: Programming Language :: Python :: 3.7
Classifier: Programming Language :: Python :: 3.8
Classifier: Programming Language :: Python :: 3.9
Classifier: Programming Language :: Python :: 3.10
Classifier: Programming Language :: Python :: 3.11
Classifier: Programming Language :: Python :: Implementation :: CPython
Classifier: Programming Language :: Python :: Implementation :: PyPy
Requires-Python: >=3.7
Requires-Dist: pip-requirements-parser
Requires-Dist: tomli; python_version < '3.11'
Requires-Dist: typer
Provides-Extra: test
Requires-Dist: coverage; extra == 'test'
Requires-Dist: mypy; extra == 'test'
Requires-Dist: pytest; extra == 'test'
